Workbook

Sheet Raw_data
A1: Company | B1: Quarter | C1: GNPA % | D1: NNPA % | E1: CRAR % | F1: AUM Growth % | G1: ROA % | H1: Cost of Funds % | I1: Source
A2: Bajaj Finance | B2: Q1 FY27 | C2: 0.0096 | D2: 0.0039 | E2: 0.209 | F2: 0.24 | G2: 0.047 | H2: 0.074 | I2: Bajaj Finance Q1 FY27 Investor Presentation -- (GNPA: p. [8]; NNPA: p. [8]; CRAR: p. [8]; AUM growth: p. [5]; ROA: p. [8]; Cost Of Funds: p. [43])
A3: Cholamandalam Finance | B3: Q1 FY27 | C3: 0.045 | D3: 0.0295 | E3: 0.1981 | F3: 0.22 | G3: 0.037 | H3: 0.067 | I3: Cholamandalam Investment and Finance Q1 FY27 Investor Presentation -- (GNPA: p. [7]; NNPA: p. [7]; CRAR: p. [7]; AUM growth: p. [7]; ROA: p. [15]; Cost Of Funds: p. [18])
A4: Shriram Finance | B4: Q1 FY27 | C4: 0.0464 | D4: 0.0233 | E4: 0.3417 | F4: 0.1526 | G4: 0.0393 | I4: Shriram Finance Q1 FY27 Investor Presentation -- (Gross Stage 3: p. [42]; Net Stage 3: p. [42]; CRAR: p. [55]; AUM growth: p. [39]; ROA: p. [55]; Cost of funds not located in Q1 FY27 investor presentation)
A5: Muthoot Finance | B5: Q1 FY27 | C5: 0.0228 | E5: 0.203 | F5: 0.43 | I5: Muthoot Finance Q1 FY27 Investor Presentation -- (Stage III Assets as % of Loan Assets: 2.28% (p. [31]); NNPA not located; CRAR: 20.3% (p. [8]); Consolidated Loan (AUM) YoY Growth: 43% (p. [5]); ROA not directly comparable; Return on Average Loan Assets: 6.09% quarterly (p. [40]). Cost of funds not identified in Q1FY27 investor presentation)
A6: Five-Star Business Finance | B6: Q1 FY27 | C6: 0.0346 | D6: 0.021 | F6: 0.04 | H6: 0.088 | I6: Five-Star Business Finance Q1 FY27 Investor Presentation -- (Gross NPA: 3.46% (p. [28]); Net NPA: 2.10% (p. [28]); AUM growth: 4% quarterly (p. [5]); Cost of Funds on the book: 8.80% in Q1 FY27, down from 8.95% in Q4 FY26 (p. [5]); CRAR not located in Q1 FY27 presentation; Return on Average AUM: 8.11% (p. [4], not directly comparable to ROA)

Sheet Clean_data
A1: Company | B1: Quarter | C1: GNPA % | D1: NNPA % | E1: CRAR % | F1: AUM Growth % | G1: ROA % | H1: Cost of Funds % | I1: Data Quality Notes
A2: Bajaj Finance | B2: Q1 FY27 | C2: 0.0096 | D2: 0.0039 | E2: 0.209 | F2: 0.24 | G2: 0.047 | H2: 0.074 | I2: GNPA/NNPA definitions may differ across companies; verify comparability before ranking
A3: Cholamandalam Finance | B3: Q1 FY27 | C3: 0.045 | D3: 0.0295 | E3: 0.1981 | F3: 0.22 | G3: 0.037 | H3: 0.067 | I3: Cholamandalam AUM growth is business AUM growth; retain the source label
A4: Shriram Finance | B4: Q1 FY27 | C4: 0.0464 | D4: 0.0233 | E4: 0.3417 | F4: 0.1526 | G4: 0.0393 | I4: Stage 3 metrics used as proxies for GNPA/NNPA; AUM growth is YoY; cost of funds unavailable
A5: Muthoot Finance | B5: Q1 FY27 | C5: 0.0228 | E5: 0.203 | F5: 0.43 | I5: Stage III assets ratio used as a GNPA proxy; NNPA, standard ROA and cost of funds unavailable
A6: Five-Star Business Finance | B6: Q1 FY27 | C6: 0.0346 | D6: 0.021 | F6: 0.04 | H6: 0.088 | I6: AUM growth is quarterly, not YoY; Return on Average AUM is not directly comparable to ROA; CRAR unavailable

Sheet Summary
A1: NBFC Peer Benchmarking Study
A3: Company | B3: GNPA / Stage 3 (%) | C3: NNPA / Net Stage 3 (%) | D3: CRAR (%) | E3: AUM Growth (%) | F3: ROA (%) | G3: Cost of Funds (%)
A4: =Clean_data!A2 -> Bajaj Finance | B4: =Clean_data!C2 -> 0.0096 | C4: =IF(Clean_data!D2="","",Clean_data!D2) -> 0.0039 | D4: =IF(Clean_data!E2="","",Clean_data!E2) -> 0.209 | E4: =IF(Clean_data!F2="","",Clean_data!F2) -> 0.24 | F4: =IF(Clean_data!G2="","",Clean_data!G2) -> 0.047 | G4: =IF(Clean_data!H2="","",Clean_data!H2) -> 0.074
A5: =Clean_data!A3 -> Cholamandalam Finance | B5: =Clean_data!C3 -> 0.045 | C5: =IF(Clean_data!D3="","",Clean_data!D3) -> 0.0295 | D5: =IF(Clean_data!E3="","",Clean_data!E3) -> 0.1981 | E5: =IF(Clean_data!F3="","",Clean_data!F3) -> 0.22 | F5: =IF(Clean_data!G3="","",Clean_data!G3) -> 0.037 | G5: =IF(Clean_data!H3="","",Clean_data!H3) -> 0.067
A6: =Clean_data!A4 -> Shriram Finance | B6: =Clean_data!C4 -> 0.0464 | C6: =IF(Clean_data!D4="","",Clean_data!D4) -> 0.0233 | D6: =IF(Clean_data!E4="","",Clean_data!E4) -> 0.3417 | E6: =IF(Clean_data!F4="","",Clean_data!F4) -> 0.1526 | F6: =IF(Clean_data!G4="","",Clean_data!G4) -> 0.0393 | G6: =IF(Clean_data!H4="","",Clean_data!H4)
A7: =Clean_data!A5 -> Muthoot Finance | B7: =Clean_data!C5 -> 0.0228 | C7: =IF(Clean_data!D5="","",Clean_data!D5) | D7: =IF(Clean_data!E5="","",Clean_data!E5) -> 0.203 | E7: =IF(Clean_data!F5="","",Clean_data!F5) -> 0.43 | F7: =IF(Clean_data!G5="","",Clean_data!G5) | G7: =IF(Clean_data!H5="","",Clean_data!H5) | K7: =G7
A8: =Clean_data!A6 -> Five-Star Business Finance | B8: =Clean_data!C6 -> 0.0346 | C8: =IF(Clean_data!D6="","",Clean_data!D6) -> 0.021 | E8: =IF(Clean_data!F6="","",Clean_data!F6) -> 0.04 | F8: =IF(Clean_data!G6="","",Clean_data!G6) | G8: =IF(Clean_data!H6="","",Clean_data!H6) -> 0.088
A10: Interpretation note: Metrics may use different definitions and reporting periods across companies. Shriram Finance Stage 3 figures and Muthoot Finance Stage III assets are not strictly equivalent to GNPA/NNPA. Five-Star AUM growth is quarterly, while other companies may report YoY% growth. Blank cells indicate unavailable or non-comparable metrics, not zero.
D28: Note: CRAR was unavailable in the investor presentations reviewed for Fiva-Star Business Finance. The chart includes only companies with available figures.
D48: Note: Cost of funds was unavailable in the investor presentations reviewed for Shriram Finance and Muthoot Finance. The chart includes only companies with available figures.
A52: Key Findings:
A54: Asset Quality | B54: Bajaj Finance reports GNPA of 0.96% and NNPA of 0.39%, indicating relatively low reported stressed assets in this peer set. However, direct comparison is limited because some peers report Stage 3 or Stage III asset measures with potentially different definitions.
A55: Capital Adequacy | B55: Shriram Finance reports CRAR of 34.17%, compared with 20.90% for Bajaj Finance and 20.30% for Muthoot Finance. Five-Star Business Finance's Q1 FY27 CRAR was not located in the presentation reviewed, so a complete five-company comparison is not possible.
A56: Growth | B56: Muthoot Finance reports 43% year-on-year loan (AUM) growth, the highest reported growth figure in this peer set. Bajaj Finance reports 24% AUM growth and Cholamandalam Finance reports 22% business AUM growth. Shriram Finance reports 15.26% year-on-year growth, while Five-Star Business Finance reports 4% quarterly growth. Five-Star's quarterly figure is not directly comparable with the year-on-year figures.
A57: Funding Cost | B57: Bajaj Finance reports a cost of funds of 7.40%, Cholamandalam Finance reports cost of funds of 6.70%, while Five-Star Business Finance reports 8.80% on the book for Q1 FY27. These figures suggest different reported funding costs, but the comparison should be interpreted cautiously because reporting definitions may differ. Cost-of-funds figures for Shriram Finance and Muthoot Finance were not located in the presentations reviewed.
A60: Conclusion: | B60: This peer benchmarking study compares five Indian NBFCs using reported asset quality, capital adequacy, AUM growth, return on assets, and cost of funds indicators for Q1 FY27. The reported figures show differences in growth, asset quality, and funding costs, but the companies cannot be ranked reliably on a single overall basis because of differences in metric definitions, reporting periods, and data availability. Further validation using standardized disclosures would improve comparability and support a more robust credit assessment.
A66: Source & Methodology:
A68: Source | B68: Company investor presentations for Q1 FY27; page references are recorded in the Raw_Data sheet.
A69: Method | B69: Figures were transcribed from investor presentations and linked to the summary sheet in Excel.
A70: Limitations | B70: Metric definitions and reporting periods may differ. Missing or non-comparable values were left blank rather than treated as zero.
A71: Scope | B71: Five Indian NBFCs: Bajaj Finance, Cholamandalam Finance, Shriram Finance, Muthoot Finance, and Five-Star Business Finance.

Sheet chart_data
A1: company | B1: Cost of Funds (%)
A2: =Summary!A4 -> Bajaj Finance | B2: =Summary!G4 -> 0.074
A3: =Summary!A5 -> Cholamandalam Finance | B3: =Summary!G5 -> 0.067
A4: =Summary!A8 -> Five-Star Business Finance | B4: =Summary!G8 -> 0.088
